ddpg/__init__.py
ddpg/actor_network.py
ddpg/actor_network_bn.py
ddpg/critic_network.py
ddpg/critic_network_bn.py
ddpg/ddpg.py
ddpg/filter_env.py
ddpg/gym_ddpg.py
ddpg/ou_noise.py
ddpg/replay_buffer.py
ddpg-0.2.0.dist-info/DESCRIPTION.rst
ddpg-0.2.0.dist-info/METADATA
ddpg-0.2.0.dist-info/RECORD
ddpg-0.2.0.dist-info/WHEEL
ddpg-0.2.0.dist-info/metadata.json
ddpg-0.2.0.dist-info/top_level.txt
