Metadata-Version: 2.0
Name: ddpg
Version: 0.2.0
Summary: Tensorflow implimentation of the DDPG algorithm
Home-page: https://github.com/maxkferg/DDPG
Author: Max Ferguson
Author-email: maxkferg@gmail.com
License: UNKNOWN
Download-URL: https://github.com/maxkferg/DDPG/archive/0.1.tar.gz
Keywords: deep deterministic policy gradient,ddpg,machine learning
Platform: UNKNOWN
Requires-Dist: matplotlib
Requires-Dist: numpy
Requires-Dist: tensorflow
